album/__init__.py
album/runner/__init__.py
album/runner/album_logging.py
album/runner/api.py
album/runner/core/__init__.py
album/runner/core/api/__init__.py
album/runner/core/api/model/__init__.py
album/runner/core/api/model/coordinates.py
album/runner/core/api/model/script_creator.py
album/runner/core/api/model/solution.py
album/runner/core/api/model/solution_script.py
album/runner/core/model/__init__.py
album/runner/core/model/coordinates.py
album/runner/core/model/script_creator.py
album/runner/core/model/solution.py
album/runner/core/model/solution_script.py
album/runner/core/schema/__init__.py
album/runner/core/schema/solution_schema.json
album_runner-0.5.4.dist-info/LICENSE
album_runner-0.5.4.dist-info/METADATA
album_runner-0.5.4.dist-info/WHEEL
album_runner-0.5.4.dist-info/top_level.txt
album_runner-0.5.4.dist-info/RECORD
